ansiwrap_hotoffthehamster/__init__.py
ansiwrap_hotoffthehamster/ansistate.py
ansiwrap_hotoffthehamster/core.py
ansiwrap_hotoffthehamster-0.8.7.dist-info/LICENSE.txt
ansiwrap_hotoffthehamster-0.8.7.dist-info/METADATA
ansiwrap_hotoffthehamster-0.8.7.dist-info/WHEEL
ansiwrap_hotoffthehamster-0.8.7.dist-info/RECORD
